searchstims/__about__.py
searchstims/__init__.py
searchstims/main.py
searchstims/make.py
searchstims/utils.py
searchstims/config/__init__.py
searchstims/config/classes.py
searchstims/config/default.ini
searchstims/config/parse.py
searchstims/config/types.ini
searchstims/stim_makers/RVvGVStimMaker.py
searchstims/stim_makers/RVvRHGVStimMaker.py
searchstims/stim_makers/TLStimMaker.py
searchstims/stim_makers/TStimMaker.py
searchstims/stim_makers/Two_v_Five_StimMaker.py
searchstims/stim_makers/__init__.py
searchstims/stim_makers/abstract_stim_maker.py
searchstims/stim_makers/xoStimMaker.py
searchstims/ttf/forced_square.ttf
searchstims-2.4.0.dist-info/LICENSE.txt
searchstims-2.4.0.dist-info/METADATA
searchstims-2.4.0.dist-info/WHEEL
searchstims-2.4.0.dist-info/entry_points.txt
searchstims-2.4.0.dist-info/top_level.txt
searchstims-2.4.0.dist-info/RECORD
