Metadata-Version: 2.1
Name: searchstims
Version: 2.4.0
Summary: Python package to make stimuli like those used in classic visual search experiments.
Home-page: https://github.com/NickleDave/searchstims
Author: David Nicholson
Author-email: nicholdav@gmail.com
License: BSD
Platform: UNKNOWN
Classifier: License :: OSI Approved :: BSD License
Classifier: Development Status :: 4 - Beta
Classifier: Programming Language :: Python
Classifier: Programming Language :: Python :: 3
Classifier: Programming Language :: Python :: 3.6
Classifier: Programming Language :: Python :: Implementation :: CPython
Requires-Python: >=3.6.0
Requires-Dist: pygame
Requires-Dist: numpy
Requires-Dist: scipy
Requires-Dist: imageio
Requires-Dist: attrs
